MANIFEST.in
README.rst
requirements.txt
setup.cfg
setup.py
djmicrosip_enviar_ventas/__init__.py
djmicrosip_enviar_ventas/__init__.pyc
djmicrosip_enviar_ventas/config.pyc
djmicrosip_enviar_ventas/forms.pyc
djmicrosip_enviar_ventas/models.pyc
djmicrosip_enviar_ventas/send_mail.py
djmicrosip_enviar_ventas/send_mail.pyc
djmicrosip_enviar_ventas/storage.pyc
djmicrosip_enviar_ventas/urls.pyc
djmicrosip_enviar_ventas/views.pyc
djmicrosip_enviar_ventas.egg-info/PKG-INFO
djmicrosip_enviar_ventas.egg-info/SOURCES.txt
djmicrosip_enviar_ventas.egg-info/dependency_links.txt
djmicrosip_enviar_ventas.egg-info/requires.txt
djmicrosip_enviar_ventas.egg-info/top_level.txt
djmicrosip_enviar_ventas/templates/djmicrosip_enviar_ventas/base.html
djmicrosip_enviar_ventas/templates/djmicrosip_enviar_ventas/busqueda_folios.html
djmicrosip_enviar_ventas/templates/djmicrosip_enviar_ventas/index.html
djmicrosip_enviar_ventas/templates/djmicrosip_enviar_ventas/preferencias.html
djmicrosip_enviar_ventas/templates/djmicrosip_enviar_ventas/ventas_diarias.html